indb_schema_biology/__init__.py
indb_schema_biology/_biolab.py
indb_schema_biology/_bionty.py
indb_schema_biology/biolab.py
indb_schema_biology/bionty.py
indb_schema_biology-0.1.0.dist-info/LICENSE
indb_schema_biology-0.1.0.dist-info/WHEEL
indb_schema_biology-0.1.0.dist-info/METADATA
indb_schema_biology-0.1.0.dist-info/RECORD
